[
  {
    "name": "Saksham Bharti",
    "leetcodeUsername": "8qr2ldT2db",
    "leetcodeProfileLink": "https://leetcode.com/u/8qr2ldT2db/"
  },
  {
    "name": "Ajay Kumar",
    "leetcodeUsername": "ajay_navodayan",
    "leetcodeProfileLink": "https://leetcode.com/u/ajay_navodayan/"
  },
  {
    "name": "Mayank Singh Tomar",
    "leetcodeUsername": "mayank_singh_tomar",
    "leetcodeProfileLink": "https://leetcode.com/u/mayank_singh_tomar/"
  },
  {
    "name": "Hemant Jangde",
    "leetcodeUsername": "H_J_1415",
    "leetcodeProfileLink": "https://leetcode.com/u/H_J_1415/"
  },
  {
    "name": "Harsh Rawat",
    "leetcodeUsername": "harzrawat",
    "leetcodeProfileLink": "https://leetcode.com/u/harzrawat/"
  },
  {
    "name": "Rashmi Kumari",
    "leetcodeUsername": "rashu2377",
    "leetcodeProfileLink": "https://leetcode.com/u/rashu2377/"
  },
  {
    "name": "Nikhil Raj Soni",
    "leetcodeUsername": "NikhilRajSoni",
    "leetcodeProfileLink": "https://leetcode.com/u/NikhilRajSoni/"
  },
  {
    "name": "Sanjay V P",
    "leetcodeUsername": "SANJAY_V_P",
    "leetcodeProfileLink": "https://leetcode.com/u/SANJAY_V_P/"
  },
  {
    "name": "Saurabh Yadav",
    "leetcodeUsername": "Saurabhrajesh23",
    "leetcodeProfileLink": "https://leetcode.com/u/Saurabhrajesh23/"
  },
  {
    "name": "Rijwith Mamidi",
    "leetcodeUsername": "Rijwith",
    "leetcodeProfileLink": "https://leetcode.com/u/Rijwith/"
  },
  {
    "name": "Pradeep Kumar",
    "leetcodeUsername": "Excited2Code",
    "leetcodeProfileLink": "https://leetcode.com/u/Excited2Code/"
  },
  {
    "name": "Jitendra Kumar",
    "leetcodeUsername": "jeet_always",
    "leetcodeProfileLink": "https://leetcode.com/u/jeet_always/"
  },
  {
    "name": "Aakash Deep",
    "leetcodeUsername": "Aakash_Deep_Sharma",
    "leetcodeProfileLink": "https://leetcode.com/u/Aakash_Deep_Sharma/"
  },
  {
    "name": "Anamika Kumari",
    "leetcodeUsername": "e_anamika",
    "leetcodeProfileLink": "https://leetcode.com/u/e_anamika/"
  },
  {
    "name": "Yashwardhan Singh Chundawat",
    "leetcodeUsername": "yashjnv",
    "leetcodeProfileLink": "https://leetcode.com/u/yashjnv/"
  },
  {
    "name": "Aakash Kumar",
    "leetcodeUsername": "sherwaljiaakash110",
    "leetcodeProfileLink": "https://leetcode.com/u/sherwaljiaakash110/"
  },
  {
    "name": "Sandeep Kumar",
    "leetcodeUsername": "saneeipk",
    "leetcodeProfileLink": "https://leetcode.com/u/saneeipk/"
  },
  {
    "name": "Satyam Kumar Pandey",
    "leetcodeUsername": "satyamkumarpandey",
    "leetcodeProfileLink": "https://leetcode.com/u/satyamkumarpandey/"
  },
  {
    "name": "Pankaj Rishi",
    "leetcodeUsername": "pankaj_rishi",
    "leetcodeProfileLink": "https://leetcode.com/u/pankaj_rishi/"
  },
  {
    "name": "Prakash Marandi",
    "leetcodeUsername": "prak290",
    "leetcodeProfileLink": "https://leetcode.com/u/prak290/"
  },
  {
    "name": "Hemant Meena",
    "leetcodeUsername": "Hevi954",
    "leetcodeProfileLink": "https://leetcode.com/u/Hevi954/"
  },
  {
    "name": "Deepali Tomar",
    "leetcodeUsername": "deepalitomar",
    "leetcodeProfileLink": "https://leetcode.com/u/deepalitomar/"
  },
  {
    "name": "Nikhil Yadav",
    "leetcodeUsername": "nikhilyadav09",
    "leetcodeProfileLink": "https://leetcode.com/u/nikhilyadav09/"
  },
  {
    "name": "Ritik Kumar",
    "leetcodeUsername": "itsritik",
    "leetcodeProfileLink": "https://leetcode.com/u/itsritik/"
  },
  {
    "name": "Ram Bhanwar Bhadiyar",
    "leetcodeUsername": "rb_bhadiyarz",
    "leetcodeProfileLink": "https://leetcode.com/u/rb_bhadiyarz/"
  },
  {
    "name": "Anshul Sharma",
    "leetcodeUsername": "Anshul_Sharma2409",
    "leetcodeProfileLink": "https://leetcode.com/u/Anshul_Sharma2409/"
  },
  {
    "name": "Rajat Malviya",
    "leetcodeUsername": "Rajat_Malviya",
    "leetcodeProfileLink": "https://leetcode.com/u/Rajat_Malviya/"
  },
  {
    "name": "Saurabh Agrahari",
    "leetcodeUsername": "maxcoder143",
    "leetcodeProfileLink": "https://leetcode.com/u/maxcoder143/"
  },
  {
    "name": "Nikhil Verma",
    "leetcodeUsername": "nikhil7618987598",
    "leetcodeProfileLink": "https://leetcode.com/u/nikhil7618987598/"
  },
  {
    "name": "Sahil Kumar",
    "leetcodeUsername": "Sahil_Kumar2005",
    "leetcodeProfileLink": "https://leetcode.com/u/Sahil_Kumar2005/"
  },
  {
    "name": "Amit Diwakar",
    "leetcodeUsername": "AmitDiwakar",
    "leetcodeProfileLink": "https://leetcode.com/u/AmitDiwakar/"
  },
  {
    "name": "Swarnali Saha",
    "leetcodeUsername": "s_sneha_smiley",
    "leetcodeProfileLink": "https://leetcode.com/u/s_sneha_smiley/"
  },
  {
    "name": "Pallavi Maurya",
    "leetcodeUsername": "Pallavi_M123",
    "leetcodeProfileLink": "https://leetcode.com/u/Pallavi_M123/"
  },
  {
    "name": "Yash Chittora",
    "leetcodeUsername": "Yash_Chittora_",
    "leetcodeProfileLink": "https://leetcode.com/u/Yash_Chittora_/"
  },
  {
    "name": "Kajol Kashipuri",
    "leetcodeUsername": "kajolkashipuri2005",
    "leetcodeProfileLink": "https://leetcode.com/u/kajolkashipuri2005/"
  },
  {
    "name": "Mayank Rai",
    "leetcodeUsername": "Mayank_Rai1774",
    "leetcodeProfileLink": "https://leetcode.com/u/Mayank_Rai1774/"
  },
  {
    "name": "Mallesh Basvant Kamati",
    "leetcodeUsername": "mallesh_kamati",
    "leetcodeProfileLink": "https://leetcode.com/u/mallesh_kamati/"
  },
  {
    "name": "Deepak Kumar",
    "leetcodeUsername": "user1394Wj",
    "leetcodeProfileLink": "https://leetcode.com/u/user1394Wj/"
  }
]